{
  "registeredUsers": [
    {
      "id": "USER_1767760876401_1_9nuet",
      "name": "ABRAHAM ALEXI PRATAMA",
      "class": "6B",
      "code": "0133714905",
      "notes": "Siswa aktif",
      "createdAt": "2026-01-07T04:41:16.401Z",
      "isActive": true
    },
    {
      "id": "USER_1767760876401_2_yr45p",
      "name": "AGHNI NAURA AZKIYA",
      "class": "6B",
      "code": "0145326124",
      "notes": "Siswa aktif",
      "createdAt": "2026-01-07T04:41:16.401Z",
      "isActive": true
    },
    {
      "id": "USER_1767760876401_3_x2uw6",
      "name": "AMELIA FAIDZATUL JANNAH",
      "class": "6B",
      "code": "0141687370",
      "notes": "Siswa aktif",
      "createdAt": "2026-01-07T04:41:16.401Z",
      "isActive": true
    },
    {
      "id": "USER_1767760876401_4_7ukhv",
      "name": "ANGELA DHINAR WIJAYANTI",
      "class": "6B",
      "code": "0149156299",
      "notes": "Siswa aktif",
      "createdAt": "2026-01-07T04:41:16.401Z",
      "isActive": true
    },
    {
      "id": "USER_1767760876401_5_axivq",
      "name": "AYUNDA DWI FEBRILIANTI",
      "class": "6B",
      "code": "0148988560",
      "notes": "Siswa aktif",
      "createdAt": "2026-01-07T04:41:16.401Z",
      "isActive": true
    },
    {
      "id": "USER_1767760876401_6_9spje",
      "name": "HABIBI UMAR SANDY",
      "class": "6B",
      "code": "0132720467",
      "notes": "Siswa aktif",
      "createdAt": "2026-01-07T04:41:16.401Z",
      "isActive": true
    },
    {
      "id": "USER_1767760876401_7_jnn43",
      "name": "IMA SAIRA",
      "class": "6B",
      "code": "0141483804",
      "notes": "Siswa aktif",
      "createdAt": "2026-01-07T04:41:16.401Z",
      "isActive": true
    },
    {
      "id": "USER_1767760876401_8_r8yvx",
      "name": "IZUL ABDUL MAJID",
      "class": "6B",
      "code": "0133923926",
      "notes": "Siswa aktif",
      "createdAt": "2026-01-07T04:41:16.401Z",
      "isActive": true
    },
    {
      "id": "USER_1767760876401_9_p9eea",
      "name": "MARCELLINA YURI ATIQAH",
      "class": "6B",
      "code": "0138861332",
      "notes": "Siswa aktif",
      "createdAt": "2026-01-07T04:41:16.401Z",
      "isActive": true
    },
    {
      "id": "USER_1767760876401_10_mz0fm",
      "name": "MARIA ULFA",
      "class": "6B",
      "code": "0135019253",
      "notes": "Siswa aktif",
      "createdAt": "2026-01-07T04:41:16.401Z",
      "isActive": true
    },
    {
      "id": "USER_1767760876401_11_pa6fr",
      "name": "MOCHAMMAD SALMAN ALFARIZI",
      "class": "6B",
      "code": "0125576554",
      "notes": "Siswa aktif",
      "createdAt": "2026-01-07T04:41:16.401Z",
      "isActive": true
    },
    {
      "id": "USER_1767760876401_12_acsle",
      "name": "MOHAMMAD RAGIL SAPUTRO",
      "class": "6B",
      "code": "0138243454",
      "notes": "Siswa aktif",
      "createdAt": "2026-01-07T04:41:16.401Z",
      "isActive": true
    },
    {
      "id": "USER_1767760876401_13_i8mea",
      "name": "MUHAMMAD ALI RIDHO",
      "class": "6B",
      "code": "3127734715",
      "notes": "Siswa aktif",
      "createdAt": "2026-01-07T04:41:16.401Z",
      "isActive": true
    },
    {
      "id": "USER_1767760876401_14_8lk1v",
      "name": "MUHAMMAD ANDIKA SAPUTRA",
      "class": "6B",
      "code": "0139936642",
      "notes": "Siswa aktif",
      "createdAt": "2026-01-07T04:41:16.401Z",
      "isActive": true
    },
    {
      "id": "USER_1767760876401_15_to10g",
      "name": "MUHAMMAD YUSRIL AKBAR",
      "class": "6B",
      "code": "3147375479",
      "notes": "Siswa aktif",
      "createdAt": "2026-01-07T04:41:16.401Z",
      "isActive": true
    },
    {
      "id": "USER_1767760876401_16_yn5xf",
      "name": "MUHAMMAD ZAINUL ANWAR",
      "class": "6B",
      "code": "0139141798",
      "notes": "Siswa aktif",
      "createdAt": "2026-01-07T04:41:16.401Z",
      "isActive": true
    },
    {
      "id": "USER_1767760876401_17_c30bc",
      "name": "NOFRI FIRMAN SYAH",
      "class": "6B",
      "code": "3133586971",
      "notes": "Siswa aktif",
      "createdAt": "2026-01-07T04:41:16.401Z",
      "isActive": true
    },
    {
      "id": "USER_1767760876401_18_89i0l",
      "name": "NURITA WULAN FITRIYANI",
      "class": "6B",
      "code": "0136013911",
      "notes": "Siswa aktif",
      "createdAt": "2026-01-07T04:41:16.401Z",
      "isActive": true
    },
    {
      "id": "USER_1767760876401_19_svo81",
      "name": "PUJI NADILA MASRUROH",
      "class": "6B",
      "code": "0131481022",
      "notes": "Siswa aktif",
      "createdAt": "2026-01-07T04:41:16.401Z",
      "isActive": true
    },
    {
      "id": "USER_1767760876401_20_w58v7",
      "name": "QUEENSHA ZALWA KHUMAIROH",
      "class": "6B",
      "code": "0146378963",
      "notes": "Siswa aktif",
      "createdAt": "2026-01-07T04:41:16.401Z",
      "isActive": true
    },
    {
      "id": "USER_1767760876401_21_0wtq7",
      "name": "RASYA FIRMANSYAH PUTRA",
      "class": "6B",
      "code": "0138965132",
      "notes": "Siswa aktif",
      "createdAt": "2026-01-07T04:41:16.401Z",
      "isActive": true
    },
    {
      "id": "USER_1767760876401_22_ha348",
      "name": "REIVAN YUDHA HABIBIL ASRAFI",
      "class": "6B",
      "code": "0137891752",
      "notes": "Siswa aktif",
      "createdAt": "2026-01-07T04:41:16.401Z",
      "isActive": true
    },
    {
      "id": "USER_1767760876401_23_9cte6",
      "name": "SAFINA JIHAN AMELIA",
      "class": "6B",
      "code": "0149504612",
      "notes": "Siswa aktif",
      "createdAt": "2026-01-07T04:41:16.401Z",
      "isActive": true
    },
    {
      "id": "USER_1767760876401_24_mb0xc",
      "name": "SASKIA QOLBI",
      "class": "6B",
      "code": "0137741158",
      "notes": "Siswa aktif",
      "createdAt": "2026-01-07T04:41:16.401Z",
      "isActive": true
    },
    {
      "id": "USER_1767760876401_25_f2h3w",
      "name": "SHAKILA NAURA SUTIRT O",
      "class": "6B",
      "code": "0137733126",
      "notes": "Siswa aktif",
      "createdAt": "2026-01-07T04:41:16.401Z",
      "isActive": true
    },
    {
      "id": "USER_1767760876401_26_d68yj",
      "name": "SHEZILYA ALDEANA ANASTASYA",
      "class": "6B",
      "code": "0137326373",
      "notes": "Siswa aktif",
      "createdAt": "2026-01-07T04:41:16.401Z",
      "isActive": true
    },
    {
      "id": "USER_1767760876401_27_p3gyj",
      "name": "TRISTAN ALVIANO",
      "class": "6B",
      "code": "0132378528",
      "notes": "Siswa aktif",
      "createdAt": "2026-01-07T04:41:16.401Z",
      "isActive": true
    },
    {
      "id": "USER_1767760876401_28_vzwrz",
      "name": "ADITYA NOVAL LANA ABIYYU",
      "class": "6A",
      "code": "0136094506",
      "notes": "Siswa aktif",
      "createdAt": "2026-01-07T04:41:16.401Z",
      "isActive": true
    },
    {
      "id": "USER_1767760876401_29_ogfmc",
      "name": "ARGA REZA SAPUTRA",
      "class": "6A",
      "code": "0136671615",
      "notes": "Siswa aktif",
      "createdAt": "2026-01-07T04:41:16.401Z",
      "isActive": true
    },
    {
      "id": "USER_1767760876401_30_j0b9u",
      "name": "DEVI OCTAVIA",
      "class": "6A",
      "code": "0139534214",
      "notes": "Siswa aktif",
      "createdAt": "2026-01-07T04:41:16.401Z",
      "isActive": true
    },
    {
      "id": "USER_1767760876401_31_c0q4t",
      "name": "ELUISANDRA SILVALITA",
      "class": "6A",
      "code": "0134832920",
      "notes": "Siswa aktif",
      "createdAt": "2026-01-07T04:41:16.401Z",
      "isActive": true
    },
    {
      "id": "USER_1767760876401_32_httvb",
      "name": "FAIQOTUL HIMMATUL ULYA",
      "class": "6A",
      "code": "0135512375",
      "notes": "Siswa aktif",
      "createdAt": "2026-01-07T04:41:16.401Z",
      "isActive": true
    },
    {
      "id": "USER_1767760876401_33_4k2d1",
      "name": "FAJAR ABIYAN HIDAYAT",
      "class": "6A",
      "code": "0133302618",
      "notes": "Siswa aktif",
      "createdAt": "2026-01-07T04:41:16.401Z",
      "isActive": true
    },
    {
      "id": "USER_1767760876401_34_ibasa",
      "name": "FEBIANA SYAFIATUL MUBAROKAH",
      "class": "6A",
      "code": "0148820538",
      "notes": "Siswa aktif",
      "createdAt": "2026-01-07T04:41:16.401Z",
      "isActive": true
    },
    {
      "id": "USER_1767760876401_35_pb673",
      "name": "GUSTI SAPUTRA DEWA",
      "class": "6A",
      "code": "3115387970",
      "notes": "Siswa aktif",
      "createdAt": "2026-01-07T04:41:16.401Z",
      "isActive": true
    },
    {
      "id": "USER_1767760876401_36_nra23",
      "name": "INDAH AUREL RAHMAWATI",
      "class": "6A",
      "code": "0134168032",
      "notes": "Siswa aktif",
      "createdAt": "2026-01-07T04:41:16.401Z",
      "isActive": true
    },
    {
      "id": "USER_1767760876401_37_hoz9r",
      "name": "JIHAN TALITA ULFA",
      "class": "6A",
      "code": "0146559759",
      "notes": "Siswa aktif",
      "createdAt": "2026-01-07T04:41:16.401Z",
      "isActive": true
    },
    {
      "id": "USER_1767760876401_38_wwhou",
      "name": "MAHIRAL QUR'ANI",
      "class": "6A",
      "code": "0134257614",
      "notes": "Siswa aktif",
      "createdAt": "2026-01-07T04:41:16.401Z",
      "isActive": true
    },
    {
      "id": "USER_1767760876401_39_xt2y4",
      "name": "MAULANA ISHAQ",
      "class": "6A",
      "code": "0143370796",
      "notes": "Siswa aktif",
      "createdAt": "2026-01-07T04:41:16.401Z",
      "isActive": true
    },
    {
      "id": "USER_1767760876401_40_cfqtb",
      "name": "MOCH AHCDAN RISKI",
      "class": "6A",
      "code": "3121598468",
      "notes": "Siswa aktif",
      "createdAt": "2026-01-07T04:41:16.401Z",
      "isActive": true
    },
    {
      "id": "USER_1767760876401_41_mke63",
      "name": "MOHAMMAD RIFQI AINUL YAKIN",
      "class": "6A",
      "code": "3149364785",
      "notes": "Siswa aktif",
      "createdAt": "2026-01-07T04:41:16.401Z",
      "isActive": true
    },
    {
      "id": "USER_1767760876401_42_nvo72",
      "name": "MUHAMMAD ALIF TRI ABDILLAH",
      "class": "6A",
      "code": "0135423952",
      "notes": "Siswa aktif",
      "createdAt": "2026-01-07T04:41:16.401Z",
      "isActive": true
    },
    {
      "id": "USER_1767760876401_43_9uno9",
      "name": "MUHAMMAD ILHAM MAULANA",
      "class": "6A",
      "code": "0133829796",
      "notes": "Siswa aktif",
      "createdAt": "2026-01-07T04:41:16.401Z",
      "isActive": true
    },
    {
      "id": "USER_1767760876401_44_fxqbk",
      "name": "MUHAMMAD NAILUN FAHMI",
      "class": "6A",
      "code": "0137645098",
      "notes": "Siswa aktif",
      "createdAt": "2026-01-07T04:41:16.401Z",
      "isActive": true
    },
    {
      "id": "USER_1767760876401_45_cjcn1",
      "name": "MUHAMMAD RAFKI AL-MAHDI",
      "class": "6A",
      "code": "0139513547",
      "notes": "Siswa aktif",
      "createdAt": "2026-01-07T04:41:16.401Z",
      "isActive": true
    },
    {
      "id": "USER_1767760876401_46_39uui",
      "name": "NAILAH NUR AZIZA",
      "class": "6A",
      "code": "0148327188",
      "notes": "Siswa aktif",
      "createdAt": "2026-01-07T04:41:16.401Z",
      "isActive": true
    },
    {
      "id": "USER_1767760876401_47_pj2tu",
      "name": "NANDA SAKIRA ARIFIN",
      "class": "6A",
      "code": "0135325884",
      "notes": "Siswa aktif",
      "createdAt": "2026-01-07T04:41:16.401Z",
      "isActive": true
    },
    {
      "id": "USER_1767760876401_48_jn2iz",
      "name": "NAYLA KENZA AZ-ZAHRA",
      "class": "6A",
      "code": "0136442172",
      "notes": "Siswa aktif",
      "createdAt": "2026-01-07T04:41:16.401Z",
      "isActive": true
    },
    {
      "id": "USER_1767760876401_49_3nmjt",
      "name": "REVI ANANDA AGUSTINA",
      "class": "6A",
      "code": "0146060720",
      "notes": "Siswa aktif",
      "createdAt": "2026-01-07T04:41:16.401Z",
      "isActive": true
    },
    {
      "id": "USER_1767760876401_50_rdf12",
      "name": "REVITA DWI ANGGRAENI",
      "class": "6A",
      "code": "0136963804",
      "notes": "Siswa aktif",
      "createdAt": "2026-01-07T04:41:16.401Z",
      "isActive": true
    },
    {
      "id": "USER_1767760876401_51_kkne3",
      "name": "RULLY GHIBRAN ARDIANSYAH",
      "class": "6A",
      "code": "0137764530",
      "notes": "Siswa aktif",
      "createdAt": "2026-01-07T04:41:16.401Z",
      "isActive": true
    },
    {
      "id": "USER_1767760876401_52_o7hwa",
      "name": "SOFIA HANNA DELISHA",
      "class": "6A",
      "code": "0144681672",
      "notes": "Siswa aktif",
      "createdAt": "2026-01-07T04:41:16.401Z",
      "isActive": true
    },
    {
      "id": "USER_1767760876401_53_v693l",
      "name": "YUDI TRI BAGUS KUSUMA FIRMANSYAH",
      "class": "6A",
      "code": "3134361827",
      "notes": "Siswa aktif",
      "createdAt": "2026-01-07T04:41:16.401Z",
      "isActive": true
    },
    {
      "id": "USER_1767760876401_54_trhmj",
      "name": "ZAKIATUL LABIBA",
      "class": "6A",
      "code": "0139962683",
      "notes": "Siswa aktif",
      "createdAt": "2026-01-07T04:41:16.401Z",
      "isActive": true
    },
    {
      "id": "USER_1767760876401_55_5zy9w",
      "name": "DWI ANGGUN WULANDARI",
      "class": "5B",
      "code": "3154361937",
      "notes": "Siswa aktif",
      "createdAt": "2026-01-07T04:41:16.401Z",
      "isActive": true
    },
    {
      "id": "USER_1767760876401_56_z1csk",
      "name": "KHOIRUL DAFFA",
      "class": "5B",
      "code": "3148866598",
      "notes": "Siswa aktif",
      "createdAt": "2026-01-07T04:41:16.401Z",
      "isActive": true
    },
    {
      "id": "USER_1767760876401_57_cjzas",
      "name": "MOCH. DIMAS OKTAVENZI",
      "class": "5B",
      "code": "3135770439",
      "notes": "Siswa aktif",
      "createdAt": "2026-01-07T04:41:16.401Z",
      "isActive": true
    },
    {
      "id": "USER_1767760876401_58_gtjs4",
      "name": "MOHAMMAD AGUS",
      "class": "5B",
      "code": "0148912904",
      "notes": "Siswa aktif",
      "createdAt": "2026-01-07T04:41:16.401Z",
      "isActive": true
    },
    {
      "id": "USER_1767760876401_59_brmfp",
      "name": "MOHAMMAD FERDI FIRMANSYAH",
      "class": "5B",
      "code": "0147747401",
      "notes": "Siswa aktif",
      "createdAt": "2026-01-07T04:41:16.401Z",
      "isActive": true
    },
    {
      "id": "USER_1767760876401_60_mqpdm",
      "name": "MOHAMMAD REVIN RAMADANI",
      "class": "5B",
      "code": "3147621269",
      "notes": "Siswa aktif",
      "createdAt": "2026-01-07T04:41:16.401Z",
      "isActive": true
    },
    {
      "id": "USER_1767760876401_61_c9ja4",
      "name": "MUHAMMAD KAFIN AL HAKIM",
      "class": "5B",
      "code": "3152357285",
      "notes": "Siswa aktif",
      "createdAt": "2026-01-07T04:41:16.401Z",
      "isActive": true
    },
    {
      "id": "USER_1767760876401_62_i7puk",
      "name": "MUHAMMAD RANDHY BACHTIAR",
      "class": "5B",
      "code": "3144972421",
      "notes": "Siswa aktif",
      "createdAt": "2026-01-07T04:41:16.401Z",
      "isActive": true
    },
    {
      "id": "USER_1767760876401_63_lg2ht",
      "name": "MUHAMMAD RENDI SAPUTRA",
      "class": "5B",
      "code": "0132349725",
      "notes": "Siswa aktif",
      "createdAt": "2026-01-07T04:41:16.401Z",
      "isActive": true
    },
    {
      "id": "USER_1767760876401_64_kygw4",
      "name": "NANDA ZAMIL ARDIANSAH",
      "class": "5B",
      "code": "0142926205",
      "notes": "Siswa aktif",
      "createdAt": "2026-01-07T04:41:16.401Z",
      "isActive": true
    },
    {
      "id": "USER_1767760876401_65_1x05u",
      "name": "NOVAL SEPTYANZAH",
      "class": "5B",
      "code": "3141364381",
      "notes": "Siswa aktif",
      "createdAt": "2026-01-07T04:41:16.401Z",
      "isActive": true
    },
    {
      "id": "USER_1767760876401_66_g6936",
      "name": "NUR MART A YUDA",
      "class": "5B",
      "code": "3145522480",
      "notes": "Siswa aktif",
      "createdAt": "2026-01-07T04:41:16.401Z",
      "isActive": true
    },
    {
      "id": "USER_1767760876401_67_5mwyv",
      "name": "RASSYA AULIA INDRI",
      "class": "5B",
      "code": "0149442551",
      "notes": "Siswa aktif",
      "createdAt": "2026-01-07T04:41:16.401Z",
      "isActive": true
    },
    {
      "id": "USER_1767760876401_68_g0j9k",
      "name": "RIKO AGUSTIA RAHMAN",
      "class": "5B",
      "code": "0142154660",
      "notes": "Siswa aktif",
      "createdAt": "2026-01-07T04:41:16.401Z",
      "isActive": true
    },
    {
      "id": "USER_1767760876401_69_x0yn2",
      "name": "SASTRI SALSABELA EKA MARETA",
      "class": "5B",
      "code": "0143951240",
      "notes": "Siswa aktif",
      "createdAt": "2026-01-07T04:41:16.401Z",
      "isActive": true
    },
    {
      "id": "USER_1767760876401_70_6abys",
      "name": "SATRIA YUDHA KEYSHANAFIQ SA'BANI",
      "class": "5B",
      "code": "0149996044",
      "notes": "Siswa aktif",
      "createdAt": "2026-01-07T04:41:16.401Z",
      "isActive": true
    },
    {
      "id": "USER_1767760876401_71_s0jm0",
      "name": "SHIFA OKTAFIA PUTRI",
      "class": "5B",
      "code": "0143932100",
      "notes": "Siswa aktif",
      "createdAt": "2026-01-07T04:41:16.401Z",
      "isActive": true
    },
    {
      "id": "USER_1767760876401_72_is6uw",
      "name": "SITI NUR AINI",
      "class": "5B",
      "code": "0144090925",
      "notes": "Siswa aktif",
      "createdAt": "2026-01-07T04:41:16.401Z",
      "isActive": true
    },
    {
      "id": "USER_1767760876401_73_81gae",
      "name": "WAFA ADITYA SYAHPUTRA PRATAMA",
      "class": "5B",
      "code": "0146517716",
      "notes": "Siswa aktif",
      "createdAt": "2026-01-07T04:41:16.401Z",
      "isActive": true
    },
    {
      "id": "USER_1767760876401_74_do8v3",
      "name": "YUSUF MAULANA HOLIKUL AKBAR",
      "class": "5B",
      "code": "0145006598",
      "notes": "Siswa aktif",
      "createdAt": "2026-01-07T04:41:16.401Z",
      "isActive": true
    },
    {
      "id": "USER_1767760876402_75_w48dg",
      "name": "ADIBATUL AQILAH KANZA",
      "class": "5A",
      "code": "0141856612",
      "notes": "Siswa aktif",
      "createdAt": "2026-01-07T04:41:16.402Z",
      "isActive": true
    },
    {
      "id": "USER_1767760876402_76_woyg9",
      "name": "AGYA NADIFATUL KOLBI",
      "class": "5A",
      "code": "0148508063",
      "notes": "Siswa aktif",
      "createdAt": "2026-01-07T04:41:16.402Z",
      "isActive": true
    },
    {
      "id": "USER_1767760876402_77_xoycl",
      "name": "AHMAD IMAM HANAFI",
      "class": "5A",
      "code": "3144461090",
      "notes": "Siswa aktif",
      "createdAt": "2026-01-07T04:41:16.402Z",
      "isActive": true
    },
    {
      "id": "USER_1767760876402_78_4mm8z",
      "name": "AISYAH NUR SYAHIRA",
      "class": "5A",
      "code": "3146779513",
      "notes": "Siswa aktif",
      "createdAt": "2026-01-07T04:41:16.402Z",
      "isActive": true
    },
    {
      "id": "USER_1767760876402_79_vpds8",
      "name": "BAGAS ADI PUTRA",
      "class": "5A",
      "code": "0143775083",
      "notes": "Siswa aktif",
      "createdAt": "2026-01-07T04:41:16.402Z",
      "isActive": true
    },
    {
      "id": "USER_1767760876402_80_61z7e",
      "name": "DIMAS TRI MULYA",
      "class": "5A",
      "code": "0148791279",
      "notes": "Siswa aktif",
      "createdAt": "2026-01-07T04:41:16.402Z",
      "isActive": true
    },
    {
      "id": "USER_1767760876402_81_0w4ip",
      "name": "DINA DWI APRILIA",
      "class": "5A",
      "code": "3141771663",
      "notes": "Siswa aktif",
      "createdAt": "2026-01-07T04:41:16.402Z",
      "isActive": true
    },
    {
      "id": "USER_1767760876402_82_xzzsp",
      "name": "FAJAR ABDUL ROHMAN",
      "class": "5A",
      "code": "3143247487",
      "notes": "Siswa aktif",
      "createdAt": "2026-01-07T04:41:16.402Z",
      "isActive": true
    },
    {
      "id": "USER_1767760876402_83_ck2oj",
      "name": "FATHAN IBROHIMI RADIYANSAH",
      "class": "5A",
      "code": "0145579649",
      "notes": "Siswa aktif",
      "createdAt": "2026-01-07T04:41:16.402Z",
      "isActive": true
    },
    {
      "id": "USER_1767760876402_84_qex0z",
      "name": "INTAN NUR AINI",
      "class": "5A",
      "code": "0146584461",
      "notes": "Siswa aktif",
      "createdAt": "2026-01-07T04:41:16.402Z",
      "isActive": true
    },
    {
      "id": "USER_1767760876402_85_mmy7o",
      "name": "MAULIDIA DWI NAFISAH",
      "class": "5A",
      "code": "0156936770",
      "notes": "Siswa aktif",
      "createdAt": "2026-01-07T04:41:16.402Z",
      "isActive": true
    },
    {
      "id": "USER_1767760876402_86_eqawu",
      "name": "MOCH. FERDIANSYAH",
      "class": "5A",
      "code": "0141325500",
      "notes": "Siswa aktif",
      "createdAt": "2026-01-07T04:41:16.402Z",
      "isActive": true
    },
    {
      "id": "USER_1767760876402_87_rn82y",
      "name": "MOCH. WILDAN FIRDAUS",
      "class": "5A",
      "code": "0144529415",
      "notes": "Siswa aktif",
      "createdAt": "2026-01-07T04:41:16.402Z",
      "isActive": true
    },
    {
      "id": "USER_1767760876402_88_6jore",
      "name": "MOCH.COKY ANDREANO",
      "class": "5A",
      "code": "0138697047",
      "notes": "Siswa aktif",
      "createdAt": "2026-01-07T04:41:16.402Z",
      "isActive": true
    },
    {
      "id": "USER_1767760876402_89_km6nd",
      "name": "MOCHAMMAD NAZRIL FIRMANSYAH",
      "class": "5A",
      "code": "0141144152",
      "notes": "Siswa aktif",
      "createdAt": "2026-01-07T04:41:16.402Z",
      "isActive": true
    },
    {
      "id": "USER_1767760876402_90_2v2zl",
      "name": "MOHAMMAD RAGIL SAPUTRA",
      "class": "5A",
      "code": "0146669551",
      "notes": "Siswa aktif",
      "createdAt": "2026-01-07T04:41:16.402Z",
      "isActive": true
    },
    {
      "id": "USER_1767760876402_91_7ermh",
      "name": "MUHAMMAD ALFIN HIDAYAT",
      "class": "5A",
      "code": "0146528050",
      "notes": "Siswa aktif",
      "createdAt": "2026-01-07T04:41:16.402Z",
      "isActive": true
    },
    {
      "id": "USER_1767760876402_92_pwill",
      "name": "MUHAMMAD SYAHRIL AKBAR",
      "class": "5A",
      "code": "3159952156",
      "notes": "Siswa aktif",
      "createdAt": "2026-01-07T04:41:16.402Z",
      "isActive": true
    },
    {
      "id": "USER_1767760876402_93_5qwgd",
      "name": "NAYLA ADELLIA",
      "class": "5A",
      "code": "0143804823",
      "notes": "Siswa aktif",
      "createdAt": "2026-01-07T04:41:16.402Z",
      "isActive": true
    },
    {
      "id": "USER_1767760876402_94_46juz",
      "name": "PUTRI ROHMATUL AISAH",
      "class": "5A",
      "code": "0141442188",
      "notes": "Siswa aktif",
      "createdAt": "2026-01-07T04:41:16.402Z",
      "isActive": true
    },
    {
      "id": "USER_1767760876402_95_pshsi",
      "name": "RAFA ILA ADDRIAZ ZAHRA",
      "class": "5A",
      "code": "0149531760",
      "notes": "Siswa aktif",
      "createdAt": "2026-01-07T04:41:16.402Z",
      "isActive": true
    },
    {
      "id": "USER_1767760876402_96_b9jck",
      "name": "RAFA MARCELLINO ARDIKA SETIAWAN",
      "class": "5A",
      "code": "RMAS_7330",
      "notes": "Siswa aktif",
      "createdAt": "2026-01-07T04:41:16.402Z",
      "isActive": true
    },
    {
      "id": "USER_1767760876402_97_1k95m",
      "name": "SASTRA BIMA SEPFRIANSYAH",
      "class": "5A",
      "code": "0142658651",
      "notes": "Siswa aktif",
      "createdAt": "2026-01-07T04:41:16.402Z",
      "isActive": true
    },
    {
      "id": "USER_1767760876402_98_7cdvd",
      "name": "SELA AYUTIA DIVA",
      "class": "5A",
      "code": "0131409270",
      "notes": "Siswa aktif",
      "createdAt": "2026-01-07T04:41:16.402Z",
      "isActive": true
    }
  ],
  "exportInfo": {
    "date": "2026-01-07T04:42:40.430Z",
    "totalUsers": 98,
    "fileType": "users-database"
  }
}